logpie/__init__.py
logpie/constants.py
logpie/handlers.py
logpie/mapping.py
logpie/stackframe.py
logpie/utils.py
logpie-5.0.1.dist-info/LICENSE
logpie-5.0.1.dist-info/METADATA
logpie-5.0.1.dist-info/WHEEL
logpie-5.0.1.dist-info/top_level.txt
logpie-5.0.1.dist-info/RECORD
